README.md
setup.py
FPlusRSA/__init__.py
FPlusRSA.egg-info/PKG-INFO
FPlusRSA.egg-info/SOURCES.txt
FPlusRSA.egg-info/dependency_links.txt
FPlusRSA.egg-info/top_level.txt