Metadata-Version: 2.1
Name: FPlusRSA
Version: 1.0.0
Summary: a small library, you can use it to implement RSA encryption and decryption and other basic methods
Home-page: UNKNOWN
Author: FPlusStudio
Author-email: qweasdghjkx@qq.com
License: UNKNOWN
Keywords: python,RSA,encryption algorithm,windows,mac,linux
Platform: UNKNOWN
Classifier: Programming Language :: Python :: 3
Classifier: License :: OSI Approved :: MIT License
Classifier: Operating System :: Unix
Classifier: Operating System :: MacOS :: MacOS X
Classifier: Operating System :: Microsoft :: Windows
